plover_application_dictionary/__init__.py
plover_application_dictionary/multiple.py
plover_application_dictionary/single.py
plover_application_dictionary-2.0.3.dist-info/LICENSE
plover_application_dictionary-2.0.3.dist-info/METADATA
plover_application_dictionary-2.0.3.dist-info/WHEEL
plover_application_dictionary-2.0.3.dist-info/entry_points.txt
plover_application_dictionary-2.0.3.dist-info/top_level.txt
plover_application_dictionary-2.0.3.dist-info/zip-safe
plover_application_dictionary-2.0.3.dist-info/RECORD
