Metadata-Version: 2.1
Name: plover-application-dictionary
Version: 2.0.3
Summary: Plover dictionary entries based on the currently focussed application
Home-page: https://github.com/Pipatooa/plover-application-dictionary
Author: Pipatooa
Author-email: pipatooa@pipatooa.co.uk
Keywords: plover plover_plugin
Requires-Python: >=3.7
License-File: LICENSE
Requires-Dist: plover (>=4.0.0dev12)
Requires-Dist: plover-application-controls (>=1.2.0)
